LICENSE.txt
README.md
setup.py
elb_log_tools/__init__.py
elb_log_tools/__version__.py
elb_log_tools/filter.py
elb_log_tools/logs.py
elb_log_tools/patterncounts.py
elb_log_tools.egg-info/PKG-INFO
elb_log_tools.egg-info/SOURCES.txt
elb_log_tools.egg-info/dependency_links.txt
elb_log_tools.egg-info/entry_points.txt
elb_log_tools.egg-info/requires.txt
elb_log_tools.egg-info/top_level.txt