Metadata-Version: 2.1
Name: elb-log-tools
Version: 0.3.0
Summary: Tools for processing logs from AWS Elastic Load Balancer
Home-page: https://github.com/pymetrics/elb-log-tools
Author: Pymetrics, Inc.
Author-email: info@pymetrics.com
License: Apache-2.0
Classifier: Development Status :: 4 - Beta
Classifier: Environment :: Console
Classifier: License :: OSI Approved :: Apache Software License
Classifier: Programming Language :: Python
Classifier: Programming Language :: Python :: 3.8
Classifier: Programming Language :: Python :: 3.9
Classifier: Programming Language :: Python :: 3.10
Classifier: Programming Language :: Python :: 3.11
Classifier: Topic :: Internet :: Log Analysis
License-File: LICENSE.txt
